monopoly/__init__.py
monopoly/banks/__init__.py
monopoly/banks/base.py
monopoly/banks/citibank/__init__.py
monopoly/banks/citibank/citibank.py
monopoly/banks/dbs/__init__.py
monopoly/banks/dbs/dbs.py
monopoly/banks/hsbc/__init__.py
monopoly/banks/hsbc/hsbc.py
monopoly/banks/ocbc/__init__.py
monopoly/banks/ocbc/ocbc.py
monopoly/banks/standard_chartered/__init__.py
monopoly/banks/standard_chartered/standard_chartered.py
monopoly/cli.py
monopoly/config.py
monopoly/constants.py
monopoly/examples/__init__.py
monopoly/examples/example_bank.py
monopoly/examples/example_statement.pdf
monopoly/examples/single_statement.py
monopoly/handler.py
monopoly/log.py
monopoly/pdf.py
monopoly/statements/__init__.py
monopoly/statements/base.py
monopoly/statements/credit_statement.py
monopoly/statements/debit_statement.py
monopoly/statements/transaction.py
monopoly/write.py
test_utils/__init__.py
test_utils/skip.py
test_utils/transactions.py
monopoly_sg-0.8.4.dist-info/LICENSE.md
monopoly_sg-0.8.4.dist-info/METADATA
monopoly_sg-0.8.4.dist-info/WHEEL
monopoly_sg-0.8.4.dist-info/entry_points.txt
monopoly_sg-0.8.4.dist-info/RECORD
