Metadata-Version: 2.1
Name: monopoly-sg
Version: 0.8.4
Summary: PDF parsing for Singaporean banks
Home-page: https://github.com/benjamin-awd/monopoly
License: MIT
Author: benjamin-awd
Author-email: benjamindornel@gmail.com
Requires-Python: >=3.11,<3.12
Classifier: Development Status :: 3 - Alpha
Classifier: License :: OSI Approved :: MIT License
Classifier: Programming Language :: Python :: 3
Classifier: Programming Language :: Python :: 3.11
Requires-Dist: click (>=8.1.7,<9.0.0)
Requires-Dist: dateparser (>=1.2.0,<2.0.0)
Requires-Dist: monopoly-core (>=0.9.3,<0.10.0)
Requires-Dist: mypy (>=1.7.1,<2.0.0)
Requires-Dist: pdftotext (>=2.2.2,<3.0.0)
Requires-Dist: pydantic (>=2.5.2,<3.0.0)
Requires-Dist: pydantic-settings (>=2.0.3,<3.0.0)
Requires-Dist: pymupdf (>=1.23.7,<2.0.0)
Requires-Dist: tabulate (>=0.9.0,<0.10.0)
Requires-Dist: tqdm (>=4.66.1,<5.0.0)
Project-URL: Repository, https://github.com/benjamin-awd/monopoly
